<?xml version="1.0" encoding="utf-8"?>
<nptrophy result="00">
  <list>
    <info npcommid="NPWR03772_00" pf="ps3">
      <types platinum="0" gold="1" silver="13" bronze="17" />
      <trophies>
        <trophy id="2" type="1">2013-08-04T14:20:46Z</trophy>
        <trophy id="3" type="1">2013-08-04T16:01:43Z</trophy>
        <trophy id="4" type="1">2013-08-04T22:45:33Z</trophy>
        <trophy id="5" type="1">2013-08-09T02:33:51Z</trophy>
        <trophy id="6" type="1">2013-08-10T01:39:35Z</trophy>
        <trophy id="7" type="1">2013-08-10T16:08:40Z</trophy>
        <trophy id="8" type="1">2013-08-10T16:08:46Z</trophy>
        <trophy id="13" type="1">2013-08-11T20:27:05Z</trophy>
        <trophy id="15" type="1">2013-08-18T15:53:24Z</trophy>
        <trophy id="16" type="0">2013-08-10T01:35:46Z</trophy>
        <trophy id="17" type="0">2013-08-16T17:50:23Z</trophy>
        <trophy id="18" type="0">2013-08-18T16:00:00Z</trophy>
        <trophy id="19" type="2">2013-08-18T16:23:20Z</trophy>
        <trophy id="20" type="1">2013-08-18T16:23:12Z</trophy>
        <trophy id="22" type="1">2013-08-11T20:28:14Z</trophy>
        <trophy id="23" type="1">2013-08-18T15:55:29Z</trophy>
        <trophy id="25" type="0">2013-08-11T17:55:24Z</trophy>
        <trophy id="26" type="0">2013-08-11T19:18:31Z</trophy>
        <trophy id="27" type="0">2013-08-18T16:03:46Z</trophy>
        <trophy id="28" type="0">2013-08-11T19:18:49Z</trophy>
        <trophy id="30" type="0">2013-08-05T00:02:51Z</trophy>
        <trophy id="31" type="0">2013-08-04T23:01:22Z</trophy>
        <trophy id="32" type="0">2013-08-04T23:04:51Z</trophy>
        <trophy id="33" type="0">2013-08-11T21:00:06Z</trophy>
        <trophy id="34" type="0">2013-08-16T17:59:14Z</trophy>
        <trophy id="36" type="0">2013-08-04T12:18:35Z</trophy>
        <trophy id="37" type="0">2013-08-04T22:24:17Z</trophy>
        <trophy id="38" type="0">2013-08-09T02:18:28Z</trophy>
        <trophy id="39" type="1">2013-08-10T15:20:41Z</trophy>
        <trophy id="40" type="0">2013-08-04T14:39:23Z</trophy>
        <trophy id="41" type="0">2013-08-04T15:01:33Z</trophy>
      </trophies>
      <last-updated>2013-08-18T16:29:34Z</last-updated>
    </info>
  </list>
</nptrophy>